preferred_pictures/__init__.py
preferred_pictures/client.py
preferred_pictures-0.5.dist-info/LICENSE.txt
preferred_pictures-0.5.dist-info/METADATA
preferred_pictures-0.5.dist-info/WHEEL
preferred_pictures-0.5.dist-info/top_level.txt
preferred_pictures-0.5.dist-info/RECORD
