Metadata-Version: 2.1
Name: preferred-pictures
Version: 0.5
Summary: A client for the PreferredPictures API
Home-page: https://github.com/preferred-pictures/python
Author: PreferredPictures
Author-email: contact@preferred.pictures
License: MIT
Download-URL: https://github.com/preferred-pictures/python/archive/v_04.tar.gz
Keywords: preferred.pictures,optimization
Platform: UNKNOWN
Classifier: Development Status :: 5 - Production/Stable
Classifier: Intended Audience :: Developers
Classifier: Environment :: Web Environment
Classifier: Topic :: Internet :: WWW/HTTP
Classifier: Topic :: Internet :: WWW/HTTP :: Dynamic Content
Classifier: License :: OSI Approved :: MIT License
Classifier: Programming Language :: Python :: 3
Classifier: Programming Language :: Python :: 3.4
Classifier: Programming Language :: Python :: 3.5
Classifier: Programming Language :: Python :: 3.6
